simplejupswap/__init__.py
simplejupswap/exceptions.py
simplejupswap/jupiter.py
simplejupswap/keys.py
simplejupswap/token_accounts.py
simplejupswap/wallet.py
simplejupswap-0.1.1.dist-info/METADATA
simplejupswap-0.1.1.dist-info/WHEEL
simplejupswap-0.1.1.dist-info/licenses/LICENSE
simplejupswap-0.1.1.dist-info/RECORD
