Metadata-Version: 2.4
Name: simplejupswap
Version: 0.1.1
Summary: Simple Solana Jupiter swaps and wallet utilities.
Project-URL: Homepage, https://github.com/jackboll59/simplejupswap
Author: jackboll59
License: MIT
License-File: LICENSE
Classifier: License :: OSI Approved :: MIT License
Classifier: Operating System :: OS Independent
Classifier: Programming Language :: Python :: 3
Requires-Python: >=3.10
Requires-Dist: requests>=2.31
Requires-Dist: solana>=0.3.0
Requires-Dist: solders<1.0,>=0.20
